NxMake-1.0.0a1.dist-info/DESCRIPTION.rst
NxMake-1.0.0a1.dist-info/METADATA
NxMake-1.0.0a1.dist-info/RECORD
NxMake-1.0.0a1.dist-info/WHEEL
NxMake-1.0.0a1.dist-info/metadata.json
NxMake-1.0.0a1.dist-info/top_level.txt
nxmake/__init__.py
nxmake/file.py
nxmake/module.py
nxmake/toolchain.py
