Metadata-Version: 2.0
Name: NxMake
Version: 1.0.0a1
Summary: Customizable build system
Home-page: https://github.com/maheshkhanwalkar/NxMake
Author: Mahesh Khanwalkar
Author-email: maheshkhanwalkar@gmail.com
License: Apache v2
Keywords: development
Platform: UNKNOWN
Classifier: Development Status :: 3 - Alpha
Classifier: Intended Audience :: Developers
Classifier: Topic :: Software Development :: Build Tools
Classifier: Programming Language :: Python :: 3.5
Requires-Python: >=3.5
